p2p_exnode_sdk/__init__.py
p2p_exnode_sdk/methods.py
p2p_exnode_sdk/models.py
p2p_exnode_sdk-0.0.2.dist-info/METADATA
p2p_exnode_sdk-0.0.2.dist-info/WHEEL
p2p_exnode_sdk-0.0.2.dist-info/top_level.txt
p2p_exnode_sdk-0.0.2.dist-info/RECORD
