Metadata-Version: 2.1
Name: p2p_exnode_sdk
Version: 0.0.2
Summary: A P2P exnode SDK
Classifier: Programming Language :: Python :: 3
Classifier: License :: OSI Approved :: MIT License
Classifier: Operating System :: OS Independent
Requires-Python: >=3.6
Requires-Dist: requests >=2.20.0
Requires-Dist: pydantic >=1.8.0
